medwave_extended_logging/__init__.py
medwave_extended_logging/definitions.py
medwave_extended_logging/fastapi/__init__.py
medwave_extended_logging/fastapi/handlers.py
medwave_extended_logging/fastapi/middlewares.py
medwave_extended_logging/fastapi/models.py
medwave_extended_logging/fastapi/utils.py
medwave_extended_logging/formatters.py
medwave_extended_logging/handlers.py
medwave_extended_logging/models.py
medwave_extended_logging/utils.py
medwave_extended_logging-0.1.3.dist-info/METADATA
medwave_extended_logging-0.1.3.dist-info/WHEEL
medwave_extended_logging-0.1.3.dist-info/RECORD
